rastersmith/__init__.py
rastersmith/core/__init__.py
rastersmith/core/core.py
rastersmith/core/countries.py
rastersmith/core/mapping.py
rastersmith/core/utils.py
rastersmith/datasets/__init__.py
rastersmith/datasets/arbitrary.py
rastersmith/datasets/atms.py
rastersmith/datasets/landsat.py
rastersmith/datasets/viirs.py
rastersmith-0.0.3.dist-info/METADATA
rastersmith-0.0.3.dist-info/RECORD
rastersmith-0.0.3.dist-info/WHEEL
rastersmith-0.0.3.dist-info/top_level.txt
