Metadata-Version: 2.1
Name: rastersmith
Version: 0.0.3
Summary: RasterSmith is a package to preprocess different NASA Earth observing satellite data products into common resolution, spatial reference, and format for easy analysis and processing across sensors.
Home-page: http://github.com/kmarkert/rastersmith
Author: Kel Markert
Author-email: kel.markert@gmail.com
License: MIT
Platform: UNKNOWN
